{
  "title": "International Journal of Intelligent Transportation Systems Research",
  "issns": [
    "13488503",
    "18688659"
  ],
  "quartile": "Q2",
  "sjr": "0,347",
  "h_index": "26",
  "type": "journal",
  "categories": "Automotive Engineering (Q2); Aerospace Engineering (Q3); Applied Mathematics (Q3); Computer Science Applications (Q3); Control and Systems Engineering (Q3); Human-Computer Interaction (Q3); Information Systems (Q3); Software (Q3); Transportation (Q3); Neuroscience (miscellaneous) (Q4)",
  "year": "2024"
}